{"intro":{"id":"10204","img":"10204.jpg","name":"乔海曙","date":"2018-05-12","inntro":"1971年7月生，安徽桐城人，经济学博士、博士后，教授、博士生导师、教育部新世纪优秀人才、闽江学者、岳麓学者，曾任湖南大学两型社会研究院院长，金融与统计学院副院长（常务）。2018年1月起，任阳光学院校长。湖南省学科带头人（金融学），湖南省“五四”青年奖章获得者，湖南省“十佳”创业导师，湖南省青年社科委副主任，湖南省互联网金融研究会常务副会长，湖南省人文社科重点研究基地负责人，国家金融与发展实验室湘江中心主任。连续担任两届湖南省青联常委，曾担任银行、信托等金融机构独立董事、顾问。任职湖南大学期间，连续破格晋升讲师（1997）、副教授（2000）、学科责任教授岗位（2002），2006年晋升教授。2000年和2010年分别荣任硕士生导师和博士生导师，是当年全校文科最年轻的硕导和博导之一。联合主编国家规划教材《金融学》，出版《互联网+金融》、《金融科技行业研究报告2017》、《中国能源替代：模式与策略》、《两型社会干部读本》等著作。近年来在《求是》、《金融研究》、《统计研究》、《人民日报》、《光明日报》以及SSCI、SCI国际期刊等发表100余篇论文，主持完成国家社科基金重点项目、国家发改委项目、湖南省重大重点项目、国家开发银行总行重大委托项目等10余项。成果获得湖南省第七届优秀社科成果一等奖（集体）等省级科研、教学成果奖等10余次。2015年9月-12月，赴加拿大阿尔伯塔大学参加教育部高校管理骨干研修班， 系统学习研究国际高校管理的先进经验。自2008年以来，开展面向地方经济社会建设重大现实问题的调查研究，中宣部国家社科规划办《成果要报》刊发研究成果，2013年9月得到中央政治局常委张高丽同志的重要批示，部分观点进入十八届三中全会公报。其他成果获得全国政协副主席、省级领导批示多次。"}}